installer/__init__.py
installer/__main__.py
installer/_core.py
installer/destinations.py
installer/exceptions.py
installer/records.py
installer/scripts.py
installer/sources.py
installer/utils.py
installer/_scripts/__init__.py
installer/_scripts/t32.exe
installer/_scripts/t64-arm.exe
installer/_scripts/t64.exe
installer/_scripts/t_arm.exe
installer/_scripts/w32.exe
installer/_scripts/w64-arm.exe
installer/_scripts/w64.exe
installer/_scripts/w_arm.exe
installer-0.5.0.dist-info/LICENSE
installer-0.5.0.dist-info/WHEEL
installer-0.5.0.dist-info/METADATA
installer-0.5.0.dist-info/RECORD
