Metadata-Version: 2.1
Name: installer
Version: 0.5.0
Summary: A library for installing Python wheels.
Author-email: Pradyun Gedam <pradyunsg@gmail.com>
Requires-Python: >=3.7
Classifier: License :: OSI Approved :: MIT License
Project-URL: GitHub, https://github.com/pradyunsg/installer
